{
  "nodes": [
    { "id": "USA", "name": "United States" },
    { "id": "UK", "name": "United Kingdom" },
    { "id": "Germany", "name": "Germany" },
    { "id": "France", "name": "France" },
    { "id": "Poland", "name": "Poland" },
    { "id": "Canada", "name": "Canada" },
    { "id": "Japan", "name": "Japan" },
    { "id": "Australia", "name": "Australia" },
    { "id": "India", "name": "India" },
    { "id": "Brazil", "name": "Brazil" },
    { "id": "China", "name": "China" },
    { "id": "Russia", "name": "Russia" },
    { "id": "SouthAfrica", "name": "South Africa" },
    { "id": "Turkey", "name": "Turkey" },
    { "id": "Iran", "name": "Iran" },
    { "id": "SaudiArabia", "name": "Saudi Arabia" },
    { "id": "Egypt", "name": "Egypt" },
    { "id": "Mexico", "name": "Mexico" },
    { "id": "SouthKorea", "name": "South Korea" },
    { "id": "Indonesia", "name": "Indonesia" },
    { "id": "Ukraine", "name": "Ukraine" },
    { "id": "Israel", "name": "Israel" },
    { "id": "Pakistan", "name": "Pakistan" },
    { "id": "Vietnam", "name": "Vietnam" },
    { "id": "Nigeria", "name": "Nigeria" },
    { "id": "Venezuela", "name": "Venezuela" },
    { "id": "EU", "name": "European Union" },
    { "id": "GlobalLeft", "name": "Global Left" },
    { "id": "Islam", "name": "Islam (Bloc)" },
    { "id": "Christianity", "name": "Christianity (Bloc)" },
    { "id": "UN", "name": "United Nations" },
    { "id": "GlobalBanks", "name": "Global Banks" },
    { "id": "PensionFunds", "name": "Pension Funds" },
    { "id": "Universities", "name": "Universities" },
    { "id": "ICHR", "name": "ICHR (Palestine)" }
  ],
  "strengthMatrix": {
    "USA": { "UK": 0.88, "Germany": 0.82, "France": 0.80, "Poland": 0.78, "Canada": 0.90, "Japan": 0.85, "Australia": 0.84, "India": 0.68, "Brazil": 0.55, "China": 0.45, "Russia": 0.40, "SouthAfrica": 0.50, "Turkey": 0.65, "Iran": 0.25, "SaudiArabia": 0.75, "Egypt": 0.60, "Mexico": 0.72, "SouthKorea": 0.82, "Indonesia": 0.50, "Ukraine": 0.75, "Israel": 0.80, "Pakistan": 0.35, "Vietnam": 0.48, "Nigeria": 0.52, "Venezuela": 0.30, "EU": 0.78, "GlobalLeft": 0.60, "Islam": 0.35, "Christianity": 0.78, "UN": 0.65, "GlobalBanks": 0.82, "PensionFunds": 0.85, "Universities": 0.88, "ICHR": 0.25 },
    "UK": { "Germany": 0.82, "France": 0.79, "Poland": 0.75, "Canada": 0.82, "Japan": 0.70, "Australia": 0.78, "India": 0.62, "Brazil": 0.58, "China": 0.48, "Russia": 0.42, "SouthAfrica": 0.55, "Turkey": 0.60, "Iran": 0.28, "SaudiArabia": 0.68, "Egypt": 0.58, "Mexico": 0.65, "SouthKorea": 0.72, "Indonesia": 0.52, "Ukraine": 0.70, "Israel": 0.72, "Pakistan": 0.38, "Vietnam": 0.45, "Nigeria": 0.50, "Venezuela": 0.35, "EU": 0.72, "GlobalLeft": 0.70, "Islam": 0.38, "Christianity": 0.72, "UN": 0.68, "GlobalBanks": 0.80, "PensionFunds": 0.78, "Universities": 0.82, "ICHR": 0.30 },
    "Germany": { "France": 0.94, "Poland": 0.85, "Canada": 0.70, "Japan": 0.65, "Australia": 0.68, "India": 0.58, "Brazil": 0.60, "China": 0.52, "Russia": 0.45, "SouthAfrica": 0.58, "Turkey": 0.58, "Iran": 0.30, "SaudiArabia": 0.62, "Egypt": 0.60, "Mexico": 0.62, "SouthKorea": 0.68, "Indonesia": 0.50, "Ukraine": 0.72, "Israel": 0.65, "Pakistan": 0.35, "Vietnam": 0.48, "Nigeria": 0.52, "Venezuela": 0.38, "EU": 0.95, "GlobalLeft": 0.72, "Islam": 0.40, "Christianity": 0.68, "UN": 0.70, "GlobalBanks": 0.78, "PensionFunds": 0.72, "Universities": 0.78, "ICHR": 0.35 },
    "France": { "Poland": 0.78, "Canada": 0.68, "Japan": 0.62, "Australia": 0.65, "India": 0.55, "Brazil": 0.62, "China": 0.50, "Russia": 0.48, "SouthAfrica": 0.60, "Turkey": 0.55, "Iran": 0.32, "SaudiArabia": 0.60, "Egypt": 0.62, "Mexico": 0.60, "SouthKorea": 0.65, "Indonesia": 0.52, "Ukraine": 0.70, "Israel": 0.62, "Pakistan": 0.38, "Vietnam": 0.45, "Nigeria": 0.55, "Venezuela": 0.40, "EU": 0.94, "GlobalLeft": 0.70, "Islam": 0.42, "Christianity": 0.65, "UN": 0.72, "GlobalBanks": 0.75, "PensionFunds": 0.68, "Universities": 0.75, "ICHR": 0.38 },
    "Poland": { "Canada": 0.65, "Japan": 0.55, "Australia": 0.60, "India": 0.52, "Brazil": 0.58, "China": 0.45, "Russia": 0.40, "SouthAfrica": 0.55, "Turkey": 0.52, "Iran": 0.25, "SaudiArabia": 0.55, "Egypt": 0.58, "Mexico": 0.58, "SouthKorea": 0.60, "Indonesia": 0.48, "Ukraine": 0.75, "Israel": 0.60, "Pakistan": 0.32, "Vietnam": 0.42, "Nigeria": 0.50, "Venezuela": 0.35, "EU": 0.85, "GlobalLeft": 0.68, "Islam": 0.35, "Christianity": 0.82, "UN": 0.65, "GlobalBanks": 0.70, "PensionFunds": 0.65, "Universities": 0.68, "ICHR": 0.32 },
    "Canada": { "Japan": 0.68, "Australia": 0.75, "India": 0.60, "Brazil": 0.65, "China": 0.48, "Russia": 0.42, "SouthAfrica": 0.62, "Turkey": 0.58, "Iran": 0.28, "SaudiArabia": 0.65, "Egypt": 0.60, "Mexico": 0.70, "SouthKorea": 0.70, "Indonesia": 0.52, "Ukraine": 0.68, "Israel": 0.68, "Pakistan": 0.35, "Vietnam": 0.45, "Nigeria": 0.55, "Venezuela": 0.40, "EU": 0.68, "GlobalLeft": 0.75, "Islam": 0.38, "Christianity": 0.70, "UN": 0.68, "GlobalBanks": 0.78, "PensionFunds": 0.80, "Universities": 0.75, "ICHR": 0.35 },
    "Japan": { "Australia": 0.82, "India": 0.70, "Brazil": 0.55, "China": 0.58, "Russia": 0.48, "SouthAfrica": 0.52, "Turkey": 0.50, "Iran": 0.30, "SaudiArabia": 0.55, "Egypt": 0.52, "Mexico": 0.58, "SouthKorea": 0.88, "Indonesia": 0.60, "Ukraine": 0.55, "Israel": 0.60, "Pakistan": 0.40, "Vietnam": 0.65, "Nigeria": 0.48, "Venezuela": 0.35, "EU": 0.65, "GlobalLeft": 0.60, "Islam": 0.35, "Christianity": 0.62, "UN": 0.62, "GlobalBanks": 0.72, "PensionFunds": 0.75, "Universities": 0.70, "ICHR": 0.28 },
    "Australia": { "India": 0.62, "Brazil": 0.58, "China": 0.50, "Russia": 0.45, "SouthAfrica": 0.58, "Turkey": 0.52, "Iran": 0.30, "SaudiArabia": 0.60, "Egypt": 0.55, "Mexico": 0.60, "SouthKorea": 0.78, "Indonesia": 0.62, "Ukraine": 0.60, "Israel": 0.65, "Pakistan": 0.38, "Vietnam": 0.55, "Nigeria": 0.52, "Venezuela": 0.38, "EU": 0.65, "GlobalLeft": 0.68, "Islam": 0.38, "Christianity": 0.65, "UN": 0.65, "GlobalBanks": 0.75, "PensionFunds": 0.72, "Universities": 0.72, "ICHR": 0.32 },
    "India": { "Brazil": 0.65, "China": 0.55, "Russia": 0.65, "SouthAfrica": 0.68, "Turkey": 0.55, "Iran": 0.45, "SaudiArabia": 0.50, "Egypt": 0.52, "Mexico": 0.58, "SouthKorea": 0.68, "Indonesia": 0.62, "Ukraine": 0.50, "Israel": 0.55, "Pakistan": 0.45, "Vietnam": 0.70, "Nigeria": 0.58, "Venezuela": 0.60, "EU": 0.55, "GlobalLeft": 0.65, "Islam": 0.48, "Christianity": 0.58, "UN": 0.68, "GlobalBanks": 0.65, "PensionFunds": 0.62, "Universities": 0.68, "ICHR": 0.45 },
    "Brazil": { "China": 0.72, "Russia": 0.65, "SouthAfrica": 0.78, "Turkey": 0.55, "Iran": 0.50, "SaudiArabia": 0.52, "Egypt": 0.58, "Mexico": 0.65, "SouthKorea": 0.58, "Indonesia": 0.60, "Ukraine": 0.48, "Israel": 0.50, "Pakistan": 0.42, "Vietnam": 0.55, "Nigeria": 0.65, "Venezuela": 0.82, "EU": 0.60, "GlobalLeft": 0.85, "Islam": 0.45, "Christianity": 0.75, "UN": 0.70, "GlobalBanks": 0.68, "PensionFunds": 0.60, "Universities": 0.65, "ICHR": 0.55 },
    "China": { "Russia": 0.85, "SouthAfrica": 0.70, "Turkey": 0.60, "Iran": 0.75, "SaudiArabia": 0.55, "Egypt": 0.52, "Mexico": 0.58, "SouthKorea": 0.62, "Indonesia": 0.68, "Ukraine": 0.40, "Israel": 0.42, "Pakistan": 0.78, "Vietnam": 0.55, "Nigeria": 0.60, "Venezuela": 0.78, "EU": 0.50, "GlobalLeft": 0.62, "Islam": 0.65, "Christianity": 0.45, "UN": 0.62, "GlobalBanks": 0.68, "PensionFunds": 0.55, "Universities": 0.60, "ICHR": 0.50 },
    "Russia": { "SouthAfrica": 0.62, "Turkey": 0.60, "Iran": 0.80, "SaudiArabia": 0.48, "Egypt": 0.50, "Mexico": 0.52, "SouthKorea": 0.50, "Indonesia": 0.55, "Ukraine": 0.25, "Israel": 0.38, "Pakistan": 0.65, "Vietnam": 0.60, "Nigeria": 0.55, "Venezuela": 0.75, "EU": 0.45, "GlobalLeft": 0.58, "Islam": 0.70, "Christianity": 0.42, "UN": 0.55, "GlobalBanks": 0.60, "PensionFunds": 0.52, "Universities": 0.55, "ICHR": 0.48 },
    "SouthAfrica": { "Turkey": 0.52, "Iran": 0.48, "SaudiArabia": 0.55, "Egypt": 0.65, "Mexico": 0.60, "SouthKorea": 0.55, "Indonesia": 0.62, "Ukraine": 0.45, "Israel": 0.48, "Pakistan": 0.50, "Vietnam": 0.52, "Nigeria": 0.72, "Venezuela": 0.70, "EU": 0.58, "GlobalLeft": 0.82, "Islam": 0.65, "Christianity": 0.60, "UN": 0.72, "GlobalBanks": 0.65, "PensionFunds": 0.58, "Universities": 0.62, "ICHR": 0.58 },
    "Turkey": { "Iran": 0.65, "SaudiArabia": 0.55, "Egypt": 0.70, "Mexico": 0.52, "SouthKorea": 0.55, "Indonesia": 0.58, "Ukraine": 0.40, "Israel": 0.45, "Pakistan": 0.60, "Vietnam": 0.50, "Nigeria": 0.55, "Venezuela": 0.52, "EU": 0.58, "GlobalLeft": 0.55, "Islam": 0.80, "Christianity": 0.48, "UN": 0.60, "GlobalBanks": 0.62, "PensionFunds": 0.58, "Universities": 0.55, "ICHR": 0.52 },
    "Iran": { "SaudiArabia": 0.35, "Egypt": 0.45, "Mexico": 0.40, "SouthKorea": 0.38, "Indonesia": 0.55, "Ukraine": 0.28, "Israel": 0.20, "Pakistan": 0.72, "Vietnam": 0.48, "Nigeria": 0.52, "Venezuela": 0.65, "EU": 0.32, "GlobalLeft": 0.50, "Islam": 0.92, "Christianity": 0.30, "UN": 0.55, "GlobalBanks": 0.52, "PensionFunds": 0.45, "Universities": 0.48, "ICHR": 0.60 },
    "SaudiArabia": { "Egypt": 0.82, "Mexico": 0.55, "SouthKorea": 0.58, "Indonesia": 0.60, "Ukraine": 0.45, "Israel": 0.65, "Pakistan": 0.52, "Vietnam": 0.50, "Nigeria": 0.58, "Venezuela": 0.48, "EU": 0.55, "GlobalLeft": 0.52, "Islam": 0.85, "Christianity": 0.52, "UN": 0.60, "GlobalBanks": 0.68, "PensionFunds": 0.62, "Universities": 0.58, "ICHR": 0.45 },
    "Egypt": { "Mexico": 0.55, "SouthKorea": 0.55, "Indonesia": 0.58, "Ukraine": 0.42, "Israel": 0.55, "Pakistan": 0.48, "Vietnam": 0.50, "Nigeria": 0.65, "Venezuela": 0.52, "EU": 0.58, "GlobalLeft": 0.55, "Islam": 0.82, "Christianity": 0.58, "UN": 0.62, "GlobalBanks": 0.60, "PensionFunds": 0.55, "Universities": 0.58, "ICHR": 0.52 },
    "Mexico": { "SouthKorea": 0.60, "Indonesia": 0.55, "Ukraine": 0.48, "Israel": 0.52, "Pakistan": 0.42, "Vietnam": 0.52, "Nigeria": 0.60, "Venezuela": 0.65, "EU": 0.60, "GlobalLeft": 0.70, "Islam": 0.48, "Christianity": 0.62, "UN": 0.65, "GlobalBanks": 0.65, "PensionFunds": 0.62, "Universities": 0.60, "ICHR": 0.45 },
    "SouthKorea": { "Indonesia": 0.62, "Ukraine": 0.52, "Israel": 0.60, "Pakistan": 0.45, "Vietnam": 0.65, "Nigeria": 0.52, "Venezuela": 0.48, "EU": 0.62, "GlobalLeft": 0.58, "Islam": 0.40, "Christianity": 0.60, "UN": 0.62, "GlobalBanks": 0.70, "PensionFunds": 0.68, "Universities": 0.65, "ICHR": 0.35 },
    "Indonesia": { "Ukraine": 0.45, "Israel": 0.42, "Pakistan": 0.60, "Vietnam": 0.68, "Nigeria": 0.62, "Venezuela": 0.55, "EU": 0.52, "GlobalLeft": 0.58, "Islam": 0.78, "Christianity": 0.52, "UN": 0.60, "GlobalBanks": 0.60, "PensionFunds": 0.55, "Universities": 0.58, "ICHR": 0.55 },
    "Ukraine": { "Israel": 0.55, "Pakistan": 0.30, "Vietnam": 0.45, "Nigeria": 0.48, "Venezuela": 0.35, "EU": 0.80, "GlobalLeft": 0.65, "Islam": 0.35, "Christianity": 0.60, "UN": 0.65, "GlobalBanks": 0.62, "PensionFunds": 0.60, "Universities": 0.62, "ICHR": 0.40 },
    "Israel": { "Pakistan": 0.25, "Vietnam": 0.40, "Nigeria": 0.45, "Venezuela": 0.30, "EU": 0.60, "GlobalLeft": 0.45, "Islam": 0.30, "Christianity": 0.65, "UN": 0.58, "GlobalBanks": 0.68, "PensionFunds": 0.65, "Universities": 0.65, "ICHR": 0.25 },
    "Pakistan": { "Vietnam": 0.55, "Nigeria": 0.50, "Venezuela": 0.48, "EU": 0.40, "GlobalLeft": 0.48, "Islam": 0.85, "Christianity": 0.38, "UN": 0.55, "GlobalBanks": 0.55, "PensionFunds": 0.52, "Universities": 0.52, "ICHR": 0.60 },
    "Vietnam": { "Nigeria": 0.55, "Venezuela": 0.52, "EU": 0.48, "GlobalLeft": 0.55, "Islam": 0.52, "Christianity": 0.48, "UN": 0.58, "GlobalBanks": 0.58, "PensionFunds": 0.55, "Universities": 0.58, "ICHR": 0.45 },
    "Nigeria": { "Venezuela": 0.60, "EU": 0.52, "GlobalLeft": 0.65, "Islam": 0.75, "Christianity": 0.80, "UN": 0.65, "GlobalBanks": 0.60, "PensionFunds": 0.58, "Universities": 0.60, "ICHR": 0.58 },
    "Venezuela": { "EU": 0.45, "GlobalLeft": 0.88, "Islam": 0.50, "Christianity": 0.62, "UN": 0.65, "GlobalBanks": 0.62, "PensionFunds": 0.55, "Universities": 0.58, "ICHR": 0.55 },

    "EU": { "GlobalLeft": 0.78, "Islam": 0.40, "Christianity": 0.68, "UN": 0.78, "GlobalBanks": 0.70, "PensionFunds": 0.65, "Universities": 0.75, "ICHR": 0.45 },
    "GlobalLeft": { "Islam": 0.55, "Christianity": 0.60, "UN": 0.72, "GlobalBanks": 0.75, "PensionFunds": 0.62, "Universities": 0.70, "ICHR": 0.72 },
    "Islam": { "Christianity": 0.35, "UN": 0.55, "GlobalBanks": 0.52, "PensionFunds": 0.45, "Universities": 0.48, "ICHR": 0.68 },
    "Christianity": { "UN": 0.62, "GlobalBanks": 0.65, "PensionFunds": 0.60, "Universities": 0.65, "ICHR": 0.40 },
    "UN": { "GlobalBanks": 0.65, "PensionFunds": 0.60, "Universities": 0.68, "ICHR": 0.75 },
    "GlobalBanks": { "PensionFunds": 0.78, "Universities": 0.70, "ICHR": 0.48 },
    "PensionFunds": { "Universities": 0.68, "ICHR": 0.42 },
    "Universities": { "ICHR": 0.50 }
  }
}
